cv_pose/__init__.py
cv_pose/arguementParser.py
cv_pose/DatasetSpecs/DatasetSpecs.py
cv_pose/DatasetSpecs/__init__.py
cv_pose/DatasetSpecs/MPII/ClimbingSplit.py
cv_pose/DatasetSpecs/MPII/MPIIDatasetSpecs.py
cv_pose/DatasetSpecs/MPII/__init__.py
cv_pose/Losses/__init__.py
cv_pose/Losses/jointMSE.py
cv_pose/Metrics/PercentageOfCorrectKeypoints.py
cv_pose/Metrics/__init__.py
cv_pose/Models/CVModel.py
cv_pose/Models/ExampleModel.py
cv_pose/Models/SoftSkipConv.py
cv_pose/Models/__init__.py
cv_pose/Preprocessors/ExamplePreprocessor.py
cv_pose/Preprocessors/OcclusionPreprocessor.py
cv_pose/Preprocessors/Preprocessor.py
cv_pose/Preprocessors/SoftGatedSkipConvBasicPreprocessor.py
cv_pose/Preprocessors/__init__.py
cv_pose-1.0.9.dist-info/METADATA
cv_pose-1.0.9.dist-info/WHEEL
cv_pose-1.0.9.dist-info/licenses/LICENSE
cv_pose-1.0.9.dist-info/RECORD
